aspose/__init__.py
aspose/note/__init__.py
aspose/note/enums.py
aspose/note/exceptions.py
aspose/note/model.py
aspose/note/_internal/__init__.py
aspose/note/_internal/ms_one/__init__.py
aspose/note/_internal/ms_one/compact_id.py
aspose/note/_internal/ms_one/errors.py
aspose/note/_internal/ms_one/object_index.py
aspose/note/_internal/ms_one/property_access.py
aspose/note/_internal/ms_one/reader.py
aspose/note/_internal/ms_one/spec_ids.py
aspose/note/_internal/ms_one/types.py
aspose/note/_internal/ms_one/entities/__init__.py
aspose/note/_internal/ms_one/entities/base.py
aspose/note/_internal/ms_one/entities/parsers.py
aspose/note/_internal/ms_one/entities/structure.py
aspose/note/_internal/onenote/__init__.py
aspose/note/_internal/onenote/document.py
aspose/note/_internal/onenote/elements.py
aspose/note/_internal/onenote/parser.py
aspose/note/_internal/onenote/pdf_export.py
aspose/note/_internal/onestore/__init__.py
aspose/note/_internal/onestore/chunk_refs.py
aspose/note/_internal/onestore/common_types.py
aspose/note/_internal/onestore/crc.py
aspose/note/_internal/onestore/errors.py
aspose/note/_internal/onestore/file_data.py
aspose/note/_internal/onestore/file_node_core.py
aspose/note/_internal/onestore/file_node_list.py
aspose/note/_internal/onestore/file_node_types.py
aspose/note/_internal/onestore/hashed_chunk_list.py
aspose/note/_internal/onestore/header.py
aspose/note/_internal/onestore/io.py
aspose/note/_internal/onestore/object_data.py
aspose/note/_internal/onestore/object_space.py
aspose/note/_internal/onestore/parse_context.py
aspose/note/_internal/onestore/summary.py
aspose/note/_internal/onestore/txn_log.py
aspose/note/saving/__init__.py
aspose_note-26.1.6.dist-info/licenses/LICENSE
aspose_note-26.1.6.dist-info/licenses/THIRD_PARTY_NOTICES.md
aspose_note-26.1.6.dist-info/METADATA
aspose_note-26.1.6.dist-info/WHEEL
aspose_note-26.1.6.dist-info/top_level.txt
aspose_note-26.1.6.dist-info/RECORD
