Metadata-Version: 2.4
Name: aspose-note
Version: 26.1.6
Summary: Aspose.Note-compatible Python API for reading OneNote (.one) files
Author: Aspose
License-Expression: LicenseRef-Aspose-Split
Project-URL: Homepage, https://github.com/aspose-note-foss/Aspose.Note-FOSS-for-Python
Project-URL: Repository, https://github.com/aspose-note-foss/Aspose.Note-FOSS-for-Python
Project-URL: Issues, https://github.com/aspose-note-foss/Aspose.Note-FOSS-for-Python/issues
Keywords: onenote,one,aspose,parser,pdf
Classifier: Programming Language :: Python :: 3
Classifier: Programming Language :: Python :: 3 :: Only
Classifier: Programming Language :: Python :: 3.10
Classifier: Programming Language :: Python :: 3.11
Classifier: Programming Language :: Python :: 3.12
Classifier: Operating System :: OS Independent
Classifier: Topic :: File Formats
Requires-Python: >=3.10
License-File: LICENSE
License-File: THIRD_PARTY_NOTICES.md
Provides-Extra: pdf
Requires-Dist: reportlab>=3.6; extra == "pdf"
Provides-Extra: dev
Requires-Dist: build>=1.2; extra == "dev"
Requires-Dist: twine>=5.0; extra == "dev"
Dynamic: license-file
